Metadata-Version: 1.2
Name: python-posix-component
Version: 0.0.1
Summary: 一些在 Unix & Linux 系统上编程的通用组件
Home-page: https://github.com/Neeky/ppc
Author: Neeky
Author-email: neeky@live.com
Maintainer: Neeky
Maintainer-email: neeky@live.com
License: UNKNOWN
Platform: UNKNOWN
Classifier: Development Status :: 4 - Beta
Classifier: Intended Audience :: Developers
Classifier: Operating System :: POSIX
Classifier: Operating System :: MacOS :: MacOS X
Classifier: Programming Language :: Python :: 3.6
Classifier: Programming Language :: Python :: 3.7
Classifier: Programming Language :: Python :: 3.8
Requires-Python: >=3.6.*
